powerlaw.py
powerlaw-1.4.5.dist-info/DESCRIPTION.rst
powerlaw-1.4.5.dist-info/METADATA
powerlaw-1.4.5.dist-info/RECORD
powerlaw-1.4.5.dist-info/WHEEL
powerlaw-1.4.5.dist-info/metadata.json
powerlaw-1.4.5.dist-info/top_level.txt
