Metadata-Version: 2.0
Name: powerlaw
Version: 1.4.5
Summary: Toolbox for testing if a probability distribution fits a power law
Home-page: http://www.github.com/jeffalstott/powerlaw
Author: Jeff Alstott
Author-email: jeffalstott@gmail.com
License: MIT
Platform: UNKNOWN
Classifier: License :: OSI Approved :: MIT License
Classifier: Programming Language :: Python
Classifier: Programming Language :: Python :: 2.7
Classifier: Programming Language :: Python :: 3
Classifier: Operating System :: OS Independent
Classifier: Topic :: Scientific/Engineering :: Mathematics
Classifier: Development Status :: 5 - Production/Stable
Classifier: Intended Audience :: Science/Research
Requires-Dist: matplotlib
Requires-Dist: mpmath
Requires-Dist: numpy
Requires-Dist: scipy
